ocf_datapipes/__init__.py
ocf_datapipes/batch/__init__.py
ocf_datapipes/batch/batches.py
ocf_datapipes/batch/merge_numpy_examples_to_batch.py
ocf_datapipes/batch/merge_numpy_modalities.py
ocf_datapipes/batch/utils.py
ocf_datapipes/batch/fake/__init__.py
ocf_datapipes/batch/fake/fake_batch.py
ocf_datapipes/batch/fake/gsp.py
ocf_datapipes/batch/fake/nwp.py
ocf_datapipes/batch/fake/pv.py
ocf_datapipes/batch/fake/satellite.py
ocf_datapipes/batch/fake/sun.py
ocf_datapipes/batch/fake/utils.py
ocf_datapipes/config/__init__.py
ocf_datapipes/config/load.py
ocf_datapipes/config/model.py
ocf_datapipes/config/save.py
ocf_datapipes/convert/__init__.py
ocf_datapipes/convert/coordinates.py
ocf_datapipes/convert/stack_xarray_to_numpy.py
ocf_datapipes/convert/numpy/__init__.py
ocf_datapipes/convert/numpy/gsp.py
ocf_datapipes/convert/numpy/pv.py
ocf_datapipes/convert/numpy_batch/__init__.py
ocf_datapipes/convert/numpy_batch/gsp.py
ocf_datapipes/convert/numpy_batch/nwp.py
ocf_datapipes/convert/numpy_batch/pv.py
ocf_datapipes/convert/numpy_batch/satellite.py
ocf_datapipes/convert/numpy_batch/sensor.py
ocf_datapipes/convert/numpy_batch/wind.py
ocf_datapipes/experimental/__init__.py
ocf_datapipes/load/__init__.py
ocf_datapipes/load/configuration.py
ocf_datapipes/load/satellite.py
ocf_datapipes/load/topographic.py
ocf_datapipes/load/gsp/__init__.py
ocf_datapipes/load/gsp/database.py
ocf_datapipes/load/gsp/gsp.py
ocf_datapipes/load/gsp/gsp_national.py
ocf_datapipes/load/gsp/utils.py
ocf_datapipes/load/nwp/__init__.py
ocf_datapipes/load/nwp/nwp.py
ocf_datapipes/load/nwp/providers/__init__.py
ocf_datapipes/load/nwp/providers/ecmwf.py
ocf_datapipes/load/nwp/providers/excarta.py
ocf_datapipes/load/nwp/providers/gfs.py
ocf_datapipes/load/nwp/providers/icon.py
ocf_datapipes/load/nwp/providers/merra2.py
ocf_datapipes/load/nwp/providers/ukv.py
ocf_datapipes/load/nwp/providers/utils.py
ocf_datapipes/load/pv/__init__.py
ocf_datapipes/load/pv/database.py
ocf_datapipes/load/pv/pv.py
ocf_datapipes-3.3.59.dist-info/licenses/LICENSE
ocf_datapipes-3.3.59.dist-info/METADATA
ocf_datapipes-3.3.59.dist-info/WHEEL
ocf_datapipes-3.3.59.dist-info/top_level.txt
ocf_datapipes-3.3.59.dist-info/RECORD
