Metadata-Version: 2.4
Name: ocf_datapipes
Version: 3.3.59
Summary: Pytorch Datapipes built for use in Open Climate Fix's forecasting work
Author: Jacob Bieker, Jack Kelly, Peter Dudfield, James Fulton
Author-email: info@openclimatefix.org
License: MIT
License-File: LICENSE
Requires-Dist: torch<2.5.0,>=2.0.0
Requires-Dist: Cartopy>=0.20.3
Requires-Dist: xarray
Requires-Dist: zarr==2.18.3
Requires-Dist: fsspec
Requires-Dist: einops
Requires-Dist: numpy
Requires-Dist: pandas
Requires-Dist: rioxarray
Requires-Dist: pathy
Requires-Dist: pyaml_env
Requires-Dist: nowcasting_datamodel>=1.5.30
Requires-Dist: gitpython
Requires-Dist: geopandas
Requires-Dist: dask
Requires-Dist: pvlib
Requires-Dist: ocf_blosc2
Requires-Dist: h5netcdf
Requires-Dist: tqdm
Requires-Dist: bottleneck
Requires-Dist: pyproj
Requires-Dist: pyresample
Requires-Dist: fastparquet
Requires-Dist: scipy
Requires-Dist: pytorch_lightning
Requires-Dist: pvlive-api
Requires-Dist: pydantic
Requires-Dist: cftime
Requires-Dist: numcodecs==0.15.1
Dynamic: author
Dynamic: author-email
Dynamic: description
Dynamic: description-content-type
Dynamic: license
Dynamic: license-file
Dynamic: requires-dist
Dynamic: summary
